pyUltroid/__init__.py
pyUltroid/__main__.py
pyUltroid/configs.py
pyUltroid/exceptions.py
pyUltroid/loader.py
pyUltroid/version.py
pyUltroid/wrappers.py
pyUltroid/functions/FastTelethon.py
pyUltroid/functions/__init__.py
pyUltroid/functions/admins.py
pyUltroid/functions/executor.py
pyUltroid/functions/gDrive.py
pyUltroid/functions/google_image.py
pyUltroid/functions/helper.py
pyUltroid/functions/info.py
pyUltroid/functions/misc.py
pyUltroid/functions/tools.py
pyUltroid/functions/ytdl.py
pyUltroid_fns-0.0.1b0.dist-info/LICENSE
pyUltroid_fns-0.0.1b0.dist-info/METADATA
pyUltroid_fns-0.0.1b0.dist-info/WHEEL
pyUltroid_fns-0.0.1b0.dist-info/top_level.txt
pyUltroid_fns-0.0.1b0.dist-info/RECORD
