Metadata-Version: 2.1
Name: pyUltroid-fns
Version: 0.0.1b0
Summary: Function based library for telegram telethon projects.
Home-page: https://github.com/TeamUltroid/pyUltroid
Author: TeamUltroid
Author-email: teamultroid@protonmail.ch
License: GNU AFFERO GENERAL PUBLIC LICENSE (v3)
Project-URL: Bug Tracker, https://github.com/TeamUltroid/pyUltroid/issues
Project-URL: Documentation, https://ultroid.tech
Project-URL: Source Code, https://github.com/TeamUltroid/pyUltroid
Platform: UNKNOWN
Classifier: Programming Language :: Python :: 3
Classifier: Programming Language :: Python :: 3.8
Classifier: Programming Language :: Python :: 3.9
Classifier: Programming Language :: Python :: 3.10
Classifier: License :: OSI Approved :: GNU General Public License v3 (GPLv3)
Classifier: Operating System :: OS Independent
Requires-Python: >3.7, <3.11
License-File: LICENSE
Requires-Dist: telethon
